cellulist/__init__.py
cellulist/_cell_list.so
cellulist/cell_list.py
cellulist/_cell_list.so.dSYM/Contents/Info.plist
cellulist/_cell_list.so.dSYM/Contents/Resources/DWARF/_cell_list.so
cellulist-0.1.1.dist-info/DESCRIPTION.rst
cellulist-0.1.1.dist-info/METADATA
cellulist-0.1.1.dist-info/metadata.json
cellulist-0.1.1.dist-info/pbr.json
cellulist-0.1.1.dist-info/RECORD
cellulist-0.1.1.dist-info/top_level.txt
cellulist-0.1.1.dist-info/WHEEL
