Metadata-Version: 2.0
Name: cellulist
Version: 0.1.1
Summary: Periodic cell list
Home-page: https://github.com/eddiejessup/cellulist
Author: Elliot Marsden
Author-email: elliot.marsden@gmail.com
License: BSD
Keywords: cellulist
Platform: UNKNOWN
Classifier: Development Status :: 4 - Beta
Classifier: Intended Audience :: Science/Research
Classifier: Topic :: Scientific/Engineering
Classifier: License :: OSI Approved :: BSD License
Classifier: Natural Language :: English
Classifier: Programming Language :: Python :: 2
Classifier: Programming Language :: Python :: 2.6
Classifier: Programming Language :: Python :: 2.7
Classifier: Programming Language :: Python :: 3
Classifier: Programming Language :: Python :: 3.3
Classifier: Programming Language :: Python :: 3.4
Requires-Dist: numpy
